{
"male":[
{
  "AT": [
      {
        "name": "Underweight",
        "total": 2.8
      },
      {
        "name": "Normal",
        "total": 47.0
      },
      {
        "name": "Overweight",
        "total": 50.2
      },
      {
        "name": "Pre-obese",
        "total": 34.8
      },
      {
        "name": "Obese",
        "total": 14.4
      }
  ],
  "PL": [
      {
      "name": "Underweight",
      "total": 2.9
      },
      {
        "name": "Normal",
        "total": 43.8
      },
      {
        "name": "Overweight",
        "total": 53.3
      },
      {
        "name": "Pre-obese",
        "total": 36.6
      },
      {
        "name": "Obese",
        "total": 16.7
      }
  ],
  "DE": [
      {
        "name": "Underweight",
        "total": 2.4
      },
      {
        "name": "Normal",
        "total": 47.0
      },
      {
        "name": "Overweight",
        "total": 50.7
      },
      {
        "name": "Pre-obese",
        "total": 34.3
      },
      {
        "name": "Obese",
        "total": 16.4
      }
  ]
}
],
"female":[
  {
    "AT": [
        {
          "name": "Underweight",
          "total": 5.8
        },
        {
          "name": "Normal",
          "total": 43.0
        },
        {
          "name": "Overweight",
          "total": 56.2
        },
        {
          "name": "Pre-obese",
          "total": 39.8
        },
        {
          "name": "Obese",
          "total": 11.4
        }
    ],
    "PL": [
        {
        "name": "Underweight",
        "total": 21.9
        },
        {
          "name": "Normal",
          "total": 41.8
        },
        {
          "name": "Overweight",
          "total": 52.3
        },
        {
          "name": "Pre-obese",
          "total": 31.6
        },
        {
          "name": "Obese",
          "total": 11.7
        }
    ],
    "DE": [
        {
          "name": "Underweight",
          "total": 1.4
        },
        {
          "name": "Normal",
          "total": 27.0
        },
        {
          "name": "Overweight",
          "total": 30.7
        },
        {
          "name": "Pre-obese",
          "total": 44.3
        },
        {
          "name": "Obese",
          "total": 56.4
        }
    ]
}
],
"total":[
{
  "AT": [
      {
        "name": "Underweight",
        "total": 1.8
      },
      {
        "name": "Normal",
        "total": 1.0
      },
      {
        "name": "Overweight",
        "total": 1.2
      },
      {
        "name": "Pre-obese",
        "total": 1.8
      },
      {
        "name": "Obese",
        "total": 1.4
      }
  ],
  "PL": [
      {
      "name": "Underweight",
      "total": 1.9
      },
      {
        "name": "Normal",
        "total": 1.8
      },
      {
        "name": "Overweight",
        "total": 1.3
      },
      {
        "name": "Pre-obese",
        "total": 1.6
      },
      {
        "name": "Obese",
        "total": 1.7
      }
  ],
  "DE": [
      {
        "name": "Underweight",
        "total": 1.4
      },
      {
        "name": "Normal",
        "total": 1.0
      },
      {
        "name": "Overweight",
        "total": 1.7
      },
      {
        "name": "Pre-obese",
        "total": 1.3
      },
      {
        "name": "Obese",
        "total": 1.4
      }
  ]
}
]
}
